pypackages/__init__.py
pypackages-0.1a6.dist-info/LICENSE
pypackages-0.1a6.dist-info/METADATA
pypackages-0.1a6.dist-info/WHEEL
pypackages-0.1a6.dist-info/top_level.txt
pypackages-0.1a6.dist-info/RECORD
